{
    "backend": "django",
    "db_name": "",
    "db_pass": "",
    "db_type": "sqlite",
    "db_user": "",
    "dbms": "1",
    "description": "generated product",
    "design": "material-dashboard",
    "docker": "0",
    "err_code": 0,
    "frontend": "",
    "heroku": "0",
    "pattern": "mvc",
    "pro": "0",
    "task_id": "b820859b-64cb-4c5c-90e7-caa60d98f4a8",
    "task_info": "Upload Sources [0%] - 387 files",
    "task_output": "b820859b-64cb-4c5c-90e7-caa60d98f4a8.zip",
    "task_result": "SUCCESS",
    "task_state": "RUNNING",
    "task_ts_end": "2022-07-05-19-50-51",
    "task_ts_start": "2022-07-05-19-50-48"
}